securicad/enterprise/__init__.py
securicad/enterprise/client.py
securicad/enterprise/deprecation.py
securicad/enterprise/exceptions.py
securicad/enterprise/metadata.py
securicad/enterprise/models.py
securicad/enterprise/organizations.py
securicad/enterprise/parsers.py
securicad/enterprise/projects.py
securicad/enterprise/py.typed
securicad/enterprise/scenarios.py
securicad/enterprise/simulations.py
securicad/enterprise/tunings.py
securicad/enterprise/users.py
securicad/enterprise/util/__init__.py
securicad/enterprise/util/parsers.py
securicad_enterprise-1.1.0.dist-info/LICENSE
securicad_enterprise-1.1.0.dist-info/METADATA
securicad_enterprise-1.1.0.dist-info/NOTICE
securicad_enterprise-1.1.0.dist-info/WHEEL
securicad_enterprise-1.1.0.dist-info/top_level.txt
securicad_enterprise-1.1.0.dist-info/RECORD
